trees/AVLTree.py
trees/BST.py
trees/BinaryTree.py
trees/Heap.py
cs46_selina-1.0.0.dist-info/LICENSE
cs46_selina-1.0.0.dist-info/METADATA
cs46_selina-1.0.0.dist-info/WHEEL
cs46_selina-1.0.0.dist-info/top_level.txt
cs46_selina-1.0.0.dist-info/RECORD
